telegram_send/__init__.py
telegram_send/telegram_send.py
telegram_send/utils.py
telegram_send/version.py
telegram_send-0.39.1.dist-info/METADATA
telegram_send-0.39.1.dist-info/WHEEL
telegram_send-0.39.1.dist-info/entry_points.txt
telegram_send-0.39.1.dist-info/licenses/LICENSE.txt
telegram_send-0.39.1.dist-info/RECORD
