Metadata-Version: 2.4
Name: telegram-send
Version: 0.39.1
Summary: Send messages and files over Telegram from the command-line.
Project-URL: homepage, https://github.com/rahiel/telegram-send
Project-URL: issues, https://github.com/rahiel/telegram-send/issues
Project-URL: documentation, https://rahiel.github.io/telegram-send/
Author-email: Rahiel Kasim <rahielkasim@gmail.com>
License-Expression: GPL-3.0-or-later
License-File: LICENSE.txt
Keywords: file,message,send,telegram
Classifier: Development Status :: 5 - Production/Stable
Classifier: Environment :: Console
Classifier: Intended Audience :: Developers
Classifier: Intended Audience :: End Users/Desktop
Classifier: License :: OSI Approved :: GNU General Public License v3 or later (GPLv3+)
Classifier: Operating System :: Microsoft :: Windows
Classifier: Operating System :: POSIX
Classifier: Programming Language :: Python :: 3.9
Classifier: Topic :: Communications :: Chat
Classifier: Topic :: Utilities
Requires-Python: >=3.10
Requires-Dist: colorama>=0.4.6; sys_platform == 'win32'
Requires-Dist: platformdirs>=4.5.1
Requires-Dist: python-telegram-bot==22.5
